cga4233de/__init__.py
cga4233de/api.py
cga4233de-0.3.0.dist-info/entry_points.txt
cga4233de-0.3.0.dist-info/WHEEL
cga4233de-0.3.0.dist-info/METADATA
cga4233de-0.3.0.dist-info/RECORD
